mediatype/__init__.py
mediatype/enums.py
mediatype/models.py
mediatype/parsers.py
mediatype-0.1.5.dist-info/LICENSE
mediatype-0.1.5.dist-info/WHEEL
mediatype-0.1.5.dist-info/METADATA
mediatype-0.1.5.dist-info/RECORD
