Metadata-Version: 2.1
Name: mediatype
Version: 0.1.5
Summary: Media Type parsing and creation
Home-page: https://github.com/tombulled/mediatype
License: MIT
Keywords: python,mimetype,mediatype,contenttype,mime
Author: Tom Bulled
Author-email: 26026015+tombulled@users.noreply.github.com
Requires-Python: >=3.8,<4.0
Classifier: License :: OSI Approved :: MIT License
Classifier: Programming Language :: Python :: 3
Classifier: Programming Language :: Python :: 3.8
Classifier: Programming Language :: Python :: 3.9
Requires-Dist: enumb (>=0.1.4,<0.2.0)
Project-URL: Documentation, https://github.com/tombulled/mediatype
Project-URL: Repository, https://github.com/tombulled/mediatype
